{"personId":"1628462","name":"Milos Teodosic","records":[{"personId":"1628462","playerName":"Milos Teodosic","building":"American Airlines Center","slug":"american-airlines-center","city":"Dallas","buildingType":"home","gameType":"Regular Season","games":1,"wins":0,"losses":1,"win_pct":0.0,"total_points":0,"ppg":0.0,"career_high":0,"first_season":2019,"last_season":2019},{"personId":"1628462","playerName":"Milos Teodosic","building":"Ball Arena","slug":"ball-arena","city":"Denver","buildingType":"home","gameType":"Regular Season","games":1,"wins":1,"losses":0,"win_pct":1.0,"total_points":11,"ppg":11.0,"career_high":11,"first_season":2018,"last_season":2018},{"personId":"1628462","playerName":"Milos Teodosic","building":"Barclays Center","slug":"barclays-center","city":"Brooklyn","buildingType":"home","gameType":"Regular Season","games":1,"wins":1,"losses":0,"win_pct":1.0,"total_points":7,"ppg":7.0,"career_high":7,"first_season":2018,"last_season":2018},{"personId":"1628462","playerName":"Milos Teodosic","building":"Bradley Center","slug":"bradley-center","city":"Milwaukee","buildingType":"home","gameType":"Regular Season","games":1,"wins":1,"losses":0,"win_pct":1.0,"total_points":15,"ppg":15.0,"career_high":15,"first_season":2018,"last_season":2018},{"personId":"1628462","playerName":"Milos Teodosic","building":"Crypto.com Arena","slug":"crypto-com-arena","city":"Los Angeles","buildingType":"home","gameType":"Regular Season","games":28,"wins":20,"losses":8,"win_pct":0.714,"total_points":241,"ppg":8.6,"career_high":15,"first_season":2018,"last_season":2019},{"personId":"1628462","playerName":"Milos Teodosic","building":"Delta Center","slug":"delta-center","city":"Salt Lake City","buildingType":"home","gameType":"Regular Season","games":1,"wins":0,"losses":1,"win_pct":0.0,"total_points":8,"ppg":8.0,"career_high":8,"first_season":2018,"last_season":2018},{"personId":"1628462","playerName":"Milos Teodosic","building":"FedExForum","slug":"fedexforum","city":"Memphis","buildingType":"home","gameType":"Regular Season","games":2,"wins":1,"losses":1,"win_pct":0.5,"total_points":27,"ppg":13.5,"career_high":18,"first_season":2018,"last_season":2018},{"personId":"1628462","playerName":"Milos Teodosic","building":"Frost Bank Center","slug":"frost-bank-center","city":"San Antonio","buildingType":"home","gameType":"Regular Season","games":2,"wins":0,"losses":2,"win_pct":0.0,"total_points":8,"ppg":4.0,"career_high":8,"first_season":2018,"last_season":2019},{"personId":"1628462","playerName":"Milos Teodosic","building":"Gainbridge Fieldhouse","slug":"gainbridge-fieldhouse","city":"Indianapolis","buildingType":"home","gameType":"Regular Season","games":1,"wins":0,"losses":1,"win_pct":0.0,"total_points":10,"ppg":10.0,"career_high":10,"first_season":2018,"last_season":2018},{"personId":"1628462","playerName":"Milos Teodosic","building":"Golden 1 Center","slug":"golden-1-center","city":"Sacramento","buildingType":"home","gameType":"Regular Season","games":2,"wins":2,"losses":0,"win_pct":1.0,"total_points":10,"ppg":5.0,"career_high":10,"first_season":2018,"last_season":2019},{"personId":"1628462","playerName":"Milos Teodosic","building":"Kaseya Center","slug":"kaseya-center","city":"Miami","buildingType":"home","gameType":"Regular Season","games":1,"wins":0,"losses":1,"win_pct":0.0,"total_points":13,"ppg":13.0,"career_high":13,"first_season":2018,"last_season":2018},{"personId":"1628462","playerName":"Milos Teodosic","building":"Kia Center","slug":"kia-center","city":"Orlando","buildingType":"home","gameType":"Regular Season","games":2,"wins":2,"losses":0,"win_pct":1.0,"total_points":14,"ppg":7.0,"career_high":8,"first_season":2018,"last_season":2019},{"personId":"1628462","playerName":"Milos Teodosic","building":"Moda Center","slug":"moda-center","city":"Portland","buildingType":"home","gameType":"Regular Season","games":2,"wins":1,"losses":1,"win_pct":0.5,"total_points":6,"ppg":3.0,"career_high":6,"first_season":2019,"last_season":2019},{"personId":"1628462","playerName":"Milos Teodosic","building":"Mortgage Matchup Center","slug":"mortgage-matchup-center","city":"Phoenix","buildingType":"home","gameType":"Regular Season","games":2,"wins":2,"losses":0,"win_pct":1.0,"total_points":11,"ppg":5.5,"career_high":8,"first_season":2018,"last_season":2019},{"personId":"1628462","playerName":"Milos Teodosic","building":"Oracle Arena","slug":"oracle-arena","city":"Oakland","buildingType":"home","gameType":"Regular Season","games":1,"wins":0,"losses":1,"win_pct":0.0,"total_points":14,"ppg":14.0,"career_high":14,"first_season":2018,"last_season":2018},{"personId":"1628462","playerName":"Milos Teodosic","building":"Paycom Center","slug":"paycom-center","city":"Oklahoma City","buildingType":"home","gameType":"Regular Season","games":3,"wins":0,"losses":3,"win_pct":0.0,"total_points":17,"ppg":5.7,"career_high":12,"first_season":2018,"last_season":2019},{"personId":"1628462","playerName":"Milos Teodosic","building":"Scotiabank Arena","slug":"scotiabank-arena","city":"Toronto","buildingType":"home","gameType":"Regular Season","games":1,"wins":1,"losses":0,"win_pct":1.0,"total_points":15,"ppg":15.0,"career_high":15,"first_season":2018,"last_season":2018},{"personId":"1628462","playerName":"Milos Teodosic","building":"Smoothie King Center","slug":"smoothie-king-center","city":"New Orleans","buildingType":"home","gameType":"Regular Season","games":1,"wins":1,"losses":0,"win_pct":1.0,"total_points":12,"ppg":12.0,"career_high":12,"first_season":2018,"last_season":2018},{"personId":"1628462","playerName":"Milos Teodosic","building":"State Farm Arena","slug":"state-farm-arena","city":"Atlanta","buildingType":"home","gameType":"Regular Season","games":1,"wins":1,"losses":0,"win_pct":1.0,"total_points":0,"ppg":0.0,"career_high":0,"first_season":2019,"last_season":2019},{"personId":"1628462","playerName":"Milos Teodosic","building":"TD Garden","slug":"td-garden","city":"Boston","buildingType":"home","gameType":"Regular Season","games":1,"wins":1,"losses":0,"win_pct":1.0,"total_points":10,"ppg":10.0,"career_high":10,"first_season":2018,"last_season":2018},{"personId":"1628462","playerName":"Milos Teodosic","building":"Target Center","slug":"target-center","city":"Minneapolis","buildingType":"home","gameType":"Regular Season","games":1,"wins":0,"losses":1,"win_pct":0.0,"total_points":10,"ppg":10.0,"career_high":10,"first_season":2018,"last_season":2018},{"personId":"1628462","playerName":"Milos Teodosic","building":"Toyota Center","slug":"toyota-center","city":"Houston","buildingType":"home","gameType":"Regular Season","games":2,"wins":1,"losses":1,"win_pct":0.5,"total_points":11,"ppg":5.5,"career_high":8,"first_season":2018,"last_season":2019},{"personId":"1628462","playerName":"Milos Teodosic","building":"United Center","slug":"united-center","city":"Chicago","buildingType":"home","gameType":"Regular Season","games":1,"wins":1,"losses":0,"win_pct":1.0,"total_points":7,"ppg":7.0,"career_high":7,"first_season":2018,"last_season":2018},{"personId":"1628462","playerName":"Milos Teodosic","building":"Xfinity Mobile Arena","slug":"xfinity-mobile-arena","city":"Philadelphia","buildingType":"home","gameType":"Regular Season","games":1,"wins":0,"losses":1,"win_pct":0.0,"total_points":0,"ppg":0.0,"career_high":0,"first_season":2019,"last_season":2019}]}