{"personId":"1629027","name":"Trae Young","records":[{"personId":"1629027","playerName":"Trae Young","building":"Amalie Arena","slug":"amalie-arena","city":"Tampa","buildingType":"home","gameType":"Regular Season","games":1,"wins":1,"losses":0,"win_pct":1.0,"total_points":37,"ppg":37.0,"career_high":37,"first_season":2021,"last_season":2021},{"personId":"1629027","playerName":"Trae Young","building":"American Airlines Center","slug":"american-airlines-center","city":"Dallas","buildingType":"home","gameType":"Regular Season","games":6,"wins":1,"losses":5,"win_pct":0.167,"total_points":121,"ppg":20.2,"career_high":25,"first_season":2019,"last_season":2025},{"personId":"1629027","playerName":"Trae Young","building":"Arena CDMX","slug":"arena-cdmx","city":"Mexico City","buildingType":"neutral","gameType":"Regular Season","games":1,"wins":1,"losses":0,"win_pct":1.0,"total_points":41,"ppg":41.0,"career_high":41,"first_season":2024,"last_season":2024},{"personId":"1629027","playerName":"Trae Young","building":"Ball Arena","slug":"ball-arena","city":"Denver","buildingType":"home","gameType":"Regular Season","games":5,"wins":1,"losses":4,"win_pct":0.2,"total_points":129,"ppg":25.8,"career_high":42,"first_season":2019,"last_season":2025},{"personId":"1629027","playerName":"Trae Young","building":"Barclays Center","slug":"barclays-center","city":"Brooklyn","buildingType":"home","gameType":"Regular Season","games":11,"wins":3,"losses":8,"win_pct":0.273,"total_points":250,"ppg":22.7,"career_high":47,"first_season":2019,"last_season":2026},{"personId":"1629027","playerName":"Trae Young","building":"Capital One Arena","slug":"capital-one-arena","city":"Washington","buildingType":"home","gameType":"Regular Season","games":14,"wins":8,"losses":6,"win_pct":0.571,"total_points":340,"ppg":24.3,"career_high":41,"first_season":2019,"last_season":2026},{"personId":"1629027","playerName":"Trae Young","building":"Chase Center","slug":"chase-center","city":"San Francisco","buildingType":"home","gameType":"Regular Season","games":4,"wins":1,"losses":3,"win_pct":0.25,"total_points":91,"ppg":22.8,"career_high":30,"first_season":2021,"last_season":2025},{"personId":"1629027","playerName":"Trae Young","building":"Crypto.com Arena","slug":"crypto-com-arena","city":"Los Angeles","buildingType":"home","gameType":"Regular Season","games":11,"wins":3,"losses":8,"win_pct":0.273,"total_points":278,"ppg":25.3,"career_high":33,"first_season":2019,"last_season":2025},{"personId":"1629027","playerName":"Trae Young","building":"Delta Center","slug":"delta-center","city":"Salt Lake City","buildingType":"home","gameType":"Regular Season","games":5,"wins":2,"losses":3,"win_pct":0.4,"total_points":110,"ppg":22.0,"career_high":28,"first_season":2019,"last_season":2025},{"personId":"1629027","playerName":"Trae Young","building":"FedExForum","slug":"fedexforum","city":"Memphis","buildingType":"home","gameType":"Regular Season","games":5,"wins":3,"losses":2,"win_pct":0.6,"total_points":115,"ppg":23.0,"career_high":36,"first_season":2019,"last_season":2025},{"personId":"1629027","playerName":"Trae Young","building":"Fiserv Forum","slug":"fiserv-forum","city":"Milwaukee","buildingType":"home","gameType":"Playoffs","games":2,"wins":1,"losses":1,"win_pct":0.5,"total_points":63,"ppg":31.5,"career_high":48,"first_season":2021,"last_season":2021},{"personId":"1629027","playerName":"Trae Young","building":"Fiserv Forum","slug":"fiserv-forum","city":"Milwaukee","buildingType":"home","gameType":"Regular Season","games":9,"wins":4,"losses":5,"win_pct":0.444,"total_points":220,"ppg":24.4,"career_high":42,"first_season":2019,"last_season":2025},{"personId":"1629027","playerName":"Trae Young","building":"Frost Bank Center","slug":"frost-bank-center","city":"San Antonio","buildingType":"home","gameType":"Regular Season","games":7,"wins":4,"losses":3,"win_pct":0.571,"total_points":182,"ppg":26.0,"career_high":45,"first_season":2019,"last_season":2025},{"personId":"1629027","playerName":"Trae Young","building":"Gainbridge Fieldhouse","slug":"gainbridge-fieldhouse","city":"Indianapolis","buildingType":"home","gameType":"Regular Season","games":11,"wins":3,"losses":8,"win_pct":0.273,"total_points":258,"ppg":23.5,"career_high":49,"first_season":2019,"last_season":2025},{"personId":"1629027","playerName":"Trae Young","building":"Golden 1 Center","slug":"golden-1-center","city":"Sacramento","buildingType":"home","gameType":"Regular Season","games":4,"wins":2,"losses":2,"win_pct":0.5,"total_points":80,"ppg":20.0,"career_high":29,"first_season":2019,"last_season":2025},{"personId":"1629027","playerName":"Trae Young","building":"Intuit Dome","slug":"intuit-dome","city":"Inglewood","buildingType":"home","gameType":"Regular Season","games":1,"wins":0,"losses":1,"win_pct":0.0,"total_points":20,"ppg":20.0,"career_high":20,"first_season":2025,"last_season":2025},{"personId":"1629027","playerName":"Trae Young","building":"Kaseya Center","slug":"kaseya-center","city":"Miami","buildingType":"home","gameType":"Playoffs","games":3,"wins":0,"losses":3,"win_pct":0.0,"total_points":44,"ppg":14.7,"career_high":25,"first_season":2022,"last_season":2022},{"personId":"1629027","playerName":"Trae Young","building":"Kaseya Center","slug":"kaseya-center","city":"Miami","buildingType":"home","gameType":"Regular Season","games":13,"wins":2,"losses":11,"win_pct":0.154,"total_points":258,"ppg":19.8,"career_high":35,"first_season":2019,"last_season":2025},{"personId":"1629027","playerName":"Trae Young","building":"Kia Center","slug":"kia-center","city":"Orlando","buildingType":"home","gameType":"Regular Season","games":13,"wins":6,"losses":7,"win_pct":0.462,"total_points":320,"ppg":24.6,"career_high":32,"first_season":2019,"last_season":2026},{"personId":"1629027","playerName":"Trae Young","building":"Little Caesars Arena","slug":"little-caesars-arena","city":"Detroit","buildingType":"home","gameType":"Regular Season","games":9,"wins":5,"losses":4,"win_pct":0.556,"total_points":234,"ppg":26.0,"career_high":38,"first_season":2019,"last_season":2025},{"personId":"1629027","playerName":"Trae Young","building":"Madison Square Garden","slug":"madison-square-garden","city":"New York","buildingType":"home","gameType":"Playoffs","games":3,"wins":2,"losses":1,"win_pct":0.667,"total_points":98,"ppg":32.7,"career_high":36,"first_season":2021,"last_season":2021},{"personId":"1629027","playerName":"Trae Young","building":"Madison Square Garden","slug":"madison-square-garden","city":"New York","buildingType":"home","gameType":"Regular Season","games":11,"wins":4,"losses":7,"win_pct":0.364,"total_points":282,"ppg":25.6,"career_high":45,"first_season":2019,"last_season":2025},{"personId":"1629027","playerName":"Trae Young","building":"Moda Center","slug":"moda-center","city":"Portland","buildingType":"home","gameType":"Regular Season","games":5,"wins":0,"losses":5,"win_pct":0.0,"total_points":176,"ppg":35.2,"career_high":56,"first_season":2019,"last_season":2025},{"personId":"1629027","playerName":"Trae Young","building":"Mortgage Matchup Center","slug":"mortgage-matchup-center","city":"Phoenix","buildingType":"home","gameType":"Regular Season","games":6,"wins":2,"losses":4,"win_pct":0.333,"total_points":139,"ppg":23.2,"career_high":31,"first_season":2019,"last_season":2025},{"personId":"1629027","playerName":"Trae Young","building":"Oracle Arena","slug":"oracle-arena","city":"Oakland","buildingType":"home","gameType":"Regular Season","games":1,"wins":0,"losses":1,"win_pct":0.0,"total_points":4,"ppg":4.0,"career_high":4,"first_season":2019,"last_season":2019},{"personId":"1629027","playerName":"Trae Young","building":"Paycom Center","slug":"paycom-center","city":"Oklahoma City","buildingType":"home","gameType":"Regular Season","games":7,"wins":2,"losses":5,"win_pct":0.286,"total_points":172,"ppg":24.6,"career_high":41,"first_season":2019,"last_season":2025},{"personId":"1629027","playerName":"Trae Young","building":"Rocket Arena","slug":"rocket-arena","city":"Cleveland","buildingType":"home","gameType":"Regular Season","games":11,"wins":3,"losses":8,"win_pct":0.273,"total_points":298,"ppg":27.1,"career_high":35,"first_season":2019,"last_season":2025},{"personId":"1629027","playerName":"Trae Young","building":"Scotiabank Arena","slug":"scotiabank-arena","city":"Toronto","buildingType":"home","gameType":"Regular Season","games":9,"wins":3,"losses":6,"win_pct":0.333,"total_points":235,"ppg":26.1,"career_high":38,"first_season":2019,"last_season":2025},{"personId":"1629027","playerName":"Trae Young","building":"Smoothie King Center","slug":"smoothie-king-center","city":"New Orleans","buildingType":"home","gameType":"Regular Season","games":6,"wins":4,"losses":2,"win_pct":0.667,"total_points":142,"ppg":23.7,"career_high":33,"first_season":2019,"last_season":2026},{"personId":"1629027","playerName":"Trae Young","building":"Spectrum Center","slug":"spectrum-center","city":"Charlotte","buildingType":"home","gameType":"Regular Season","games":13,"wins":5,"losses":8,"win_pct":0.385,"total_points":264,"ppg":20.3,"career_high":31,"first_season":2019,"last_season":2026},{"personId":"1629027","playerName":"Trae Young","building":"State Farm Arena","slug":"state-farm-arena","city":"Atlanta","buildingType":"home","gameType":"Playoffs","games":12,"wins":5,"losses":7,"win_pct":0.417,"total_points":314,"ppg":26.2,"career_high":35,"first_season":2021,"last_season":2023},{"personId":"1629027","playerName":"Trae Young","building":"State Farm Arena","slug":"state-farm-arena","city":"Atlanta","buildingType":"home","gameType":"Regular Season","games":251,"wins":133,"losses":118,"win_pct":0.53,"total_points":6473,"ppg":25.8,"career_high":50,"first_season":2019,"last_season":2026},{"personId":"1629027","playerName":"Trae Young","building":"T-Mobile Arena","slug":"t-mobile-arena","city":"Las Vegas","buildingType":"neutral","gameType":"Regular Season","games":1,"wins":0,"losses":1,"win_pct":0.0,"total_points":35,"ppg":35.0,"career_high":35,"first_season":2025,"last_season":2025},{"personId":"1629027","playerName":"Trae Young","building":"TD Garden","slug":"td-garden","city":"Boston","buildingType":"home","gameType":"Playoffs","games":3,"wins":1,"losses":2,"win_pct":0.333,"total_points":78,"ppg":26.0,"career_high":38,"first_season":2023,"last_season":2023},{"personId":"1629027","playerName":"Trae Young","building":"TD Garden","slug":"td-garden","city":"Boston","buildingType":"home","gameType":"Regular Season","games":11,"wins":2,"losses":9,"win_pct":0.182,"total_points":287,"ppg":26.1,"career_high":40,"first_season":2019,"last_season":2026},{"personId":"1629027","playerName":"Trae Young","building":"Target Center","slug":"target-center","city":"Minneapolis","buildingType":"home","gameType":"Regular Season","games":6,"wins":4,"losses":2,"win_pct":0.667,"total_points":174,"ppg":29.0,"career_high":43,"first_season":2019,"last_season":2024},{"personId":"1629027","playerName":"Trae Young","building":"Toyota Center","slug":"toyota-center","city":"Houston","buildingType":"home","gameType":"Regular Season","games":7,"wins":3,"losses":4,"win_pct":0.429,"total_points":207,"ppg":29.6,"career_high":44,"first_season":2019,"last_season":2025},{"personId":"1629027","playerName":"Trae Young","building":"United Center","slug":"united-center","city":"Chicago","buildingType":"home","gameType":"Regular Season","games":10,"wins":3,"losses":7,"win_pct":0.3,"total_points":203,"ppg":20.3,"career_high":37,"first_season":2019,"last_season":2026},{"personId":"1629027","playerName":"Trae Young","building":"Xfinity Mobile Arena","slug":"xfinity-mobile-arena","city":"Philadelphia","buildingType":"home","gameType":"Playoffs","games":4,"wins":3,"losses":1,"win_pct":0.75,"total_points":116,"ppg":29.0,"career_high":39,"first_season":2021,"last_season":2021},{"personId":"1629027","playerName":"Trae Young","building":"Xfinity Mobile Arena","slug":"xfinity-mobile-arena","city":"Philadelphia","buildingType":"home","gameType":"Regular Season","games":9,"wins":3,"losses":6,"win_pct":0.333,"total_points":220,"ppg":24.4,"career_high":37,"first_season":2019,"last_season":2025}]}