{"personId":"1641788","name":"Alex Fudge","records":[{"personId":"1641788","playerName":"Alex Fudge","building":"American Airlines Center","slug":"american-airlines-center","city":"Dallas","buildingType":"home","gameType":"Regular Season","games":1,"wins":0,"losses":1,"win_pct":0.0,"total_points":0,"ppg":0.0,"career_high":0,"first_season":2024,"last_season":2024},{"personId":"1641788","playerName":"Alex Fudge","building":"Kia Center","slug":"kia-center","city":"Orlando","buildingType":"home","gameType":"Regular Season","games":1,"wins":0,"losses":1,"win_pct":0.0,"total_points":0,"ppg":0.0,"career_high":0,"first_season":2024,"last_season":2024},{"personId":"1641788","playerName":"Alex Fudge","building":"Little Caesars Arena","slug":"little-caesars-arena","city":"Detroit","buildingType":"home","gameType":"Regular Season","games":1,"wins":1,"losses":0,"win_pct":1.0,"total_points":0,"ppg":0.0,"career_high":0,"first_season":2024,"last_season":2024},{"personId":"1641788","playerName":"Alex Fudge","building":"Paycom Center","slug":"paycom-center","city":"Oklahoma City","buildingType":"home","gameType":"Regular Season","games":2,"wins":0,"losses":2,"win_pct":0.0,"total_points":13,"ppg":6.5,"career_high":11,"first_season":2024,"last_season":2024},{"personId":"1641788","playerName":"Alex Fudge","building":"Xfinity Mobile Arena","slug":"xfinity-mobile-arena","city":"Philadelphia","buildingType":"home","gameType":"Regular Season","games":1,"wins":0,"losses":1,"win_pct":0.0,"total_points":2,"ppg":2.0,"career_high":2,"first_season":2024,"last_season":2024}],"arena_draw":[],"draw_label":"2026 season only"}