{"personId":"77588","name":"Larry Micheaux","records":[{"personId":"77588","playerName":"Larry Micheaux","building":"Arizona Veterans Memorial Coliseum","slug":"arizona-veterans-memorial-coliseum","city":"Phoenix","city_slug":"phoenix","buildingType":"home","gameType":"Regular Season","games":4,"wins":1,"losses":3,"win_pct":0.25,"total_points":15,"ppg":3.8,"career_high":7,"first_season":1984,"last_season":1985},{"personId":"77588","playerName":"Larry Micheaux","building":"Boston Garden","slug":"boston-garden","city":"Boston","city_slug":"boston","buildingType":"home","gameType":"Regular Season","games":1,"wins":0,"losses":1,"win_pct":0.0,"total_points":7,"ppg":7.0,"career_high":7,"first_season":1985,"last_season":1985},{"personId":"77588","playerName":"Larry Micheaux","building":"Capital Centre","slug":"capital-centre","city":"Landover","city_slug":"landover","buildingType":"home","gameType":"Regular Season","games":2,"wins":0,"losses":2,"win_pct":0.0,"total_points":0,"ppg":0.0,"career_high":0,"first_season":1985,"last_season":1985},{"personId":"77588","playerName":"Larry Micheaux","building":"Chicago Stadium","slug":"chicago-stadium","city":"Chicago","city_slug":"chicago","buildingType":"home","gameType":"Regular Season","games":1,"wins":0,"losses":1,"win_pct":0.0,"total_points":0,"ppg":0.0,"career_high":0,"first_season":1985,"last_season":1985},{"personId":"77588","playerName":"Larry Micheaux","building":"HemisFair Arena","slug":"hemisfair-arena","city":"San Antonio","city_slug":"san-antonio","buildingType":"home","gameType":"Regular Season","games":4,"wins":2,"losses":2,"win_pct":0.5,"total_points":7,"ppg":1.8,"career_high":5,"first_season":1984,"last_season":1985},{"personId":"77588","playerName":"Larry Micheaux","building":"Kemper Arena","slug":"kemper-arena","city":"Kansas City","city_slug":"kansas-city","buildingType":"home","gameType":"Playoffs","games":1,"wins":0,"losses":1,"win_pct":0.0,"total_points":16,"ppg":16.0,"career_high":16,"first_season":1984,"last_season":1984},{"personId":"77588","playerName":"Larry Micheaux","building":"Kemper Arena","slug":"kemper-arena","city":"Kansas City","city_slug":"kansas-city","buildingType":"home","gameType":"Regular Season","games":17,"wins":14,"losses":3,"win_pct":0.824,"total_points":63,"ppg":3.7,"career_high":15,"first_season":1984,"last_season":1985},{"personId":"77588","playerName":"Larry Micheaux","building":"Kingdome","slug":"kingdome","city":"Seattle","city_slug":"seattle","buildingType":"home","gameType":"Regular Season","games":2,"wins":1,"losses":1,"win_pct":0.5,"total_points":12,"ppg":6.0,"career_high":12,"first_season":1984,"last_season":1985},{"personId":"77588","playerName":"Larry Micheaux","building":"MECCA Arena","slug":"mecca-arena","city":"Milwaukee","city_slug":"milwaukee","buildingType":"home","gameType":"Regular Season","games":8,"wins":8,"losses":0,"win_pct":1.0,"total_points":15,"ppg":1.9,"career_high":7,"first_season":1985,"last_season":1985},{"personId":"77588","playerName":"Larry Micheaux","building":"Market Square Arena","slug":"market-square-arena","city":"Indianapolis","city_slug":"indianapolis","buildingType":"home","gameType":"Regular Season","games":1,"wins":0,"losses":1,"win_pct":0.0,"total_points":0,"ppg":0.0,"career_high":0,"first_season":1985,"last_season":1985},{"personId":"77588","playerName":"Larry Micheaux","building":"McNichols Sports Arena","slug":"mcnichols-sports-arena","city":"Denver","city_slug":"denver","buildingType":"home","gameType":"Regular Season","games":2,"wins":0,"losses":2,"win_pct":0.0,"total_points":9,"ppg":4.5,"career_high":6,"first_season":1984,"last_season":1985},{"personId":"77588","playerName":"Larry Micheaux","building":"Memorial Coliseum","slug":"memorial-coliseum","city":"Portland","city_slug":"portland","buildingType":"home","gameType":"Regular Season","games":4,"wins":0,"losses":4,"win_pct":0.0,"total_points":12,"ppg":3.0,"career_high":5,"first_season":1984,"last_season":1985},{"personId":"77588","playerName":"Larry Micheaux","building":"Oracle Arena","slug":"oracle-arena","city":"Oakland","city_slug":"oakland","buildingType":"home","gameType":"Regular Season","games":4,"wins":1,"losses":3,"win_pct":0.25,"total_points":2,"ppg":0.5,"career_high":2,"first_season":1984,"last_season":1985},{"personId":"77588","playerName":"Larry Micheaux","building":"Pontiac Silverdome","slug":"pontiac-silverdome","city":"Pontiac","city_slug":"pontiac","buildingType":"home","gameType":"Regular Season","games":3,"wins":0,"losses":3,"win_pct":0.0,"total_points":13,"ppg":4.3,"career_high":7,"first_season":1984,"last_season":1985},{"personId":"77588","playerName":"Larry Micheaux","building":"Reunion Arena","slug":"reunion-arena","city":"Dallas","city_slug":"dallas","buildingType":"home","gameType":"Regular Season","games":5,"wins":1,"losses":4,"win_pct":0.2,"total_points":19,"ppg":3.8,"career_high":12,"first_season":1984,"last_season":1985},{"personId":"77588","playerName":"Larry Micheaux","building":"Richfield Coliseum","slug":"richfield-coliseum","city":"Richfield","city_slug":"richfield","buildingType":"home","gameType":"Regular Season","games":2,"wins":2,"losses":0,"win_pct":1.0,"total_points":2,"ppg":1.0,"career_high":2,"first_season":1984,"last_season":1985},{"personId":"77588","playerName":"Larry Micheaux","building":"Salt Palace","slug":"salt-palace","city":"Salt Lake City","city_slug":"salt-lake-city","buildingType":"home","gameType":"Playoffs","games":2,"wins":1,"losses":1,"win_pct":0.5,"total_points":0,"ppg":0.0,"career_high":0,"first_season":1985,"last_season":1985},{"personId":"77588","playerName":"Larry Micheaux","building":"Salt Palace","slug":"salt-palace","city":"Salt Lake City","city_slug":"salt-lake-city","buildingType":"home","gameType":"Regular Season","games":4,"wins":1,"losses":3,"win_pct":0.25,"total_points":8,"ppg":2.0,"career_high":4,"first_season":1984,"last_season":1985},{"personId":"77588","playerName":"Larry Micheaux","building":"San Diego Sports Arena","slug":"san-diego-sports-arena","city":"San Diego","city_slug":"san-diego","buildingType":"home","gameType":"Regular Season","games":2,"wins":1,"losses":1,"win_pct":0.5,"total_points":10,"ppg":5.0,"career_high":10,"first_season":1984,"last_season":1984},{"personId":"77588","playerName":"Larry Micheaux","building":"The Forum","slug":"the-forum","city":"Inglewood","city_slug":"inglewood","buildingType":"home","gameType":"Playoffs","games":2,"wins":0,"losses":2,"win_pct":0.0,"total_points":14,"ppg":7.0,"career_high":8,"first_season":1984,"last_season":1984},{"personId":"77588","playerName":"Larry Micheaux","building":"The Forum","slug":"the-forum","city":"Inglewood","city_slug":"inglewood","buildingType":"home","gameType":"Regular Season","games":3,"wins":1,"losses":2,"win_pct":0.333,"total_points":12,"ppg":4.0,"career_high":6,"first_season":1984,"last_season":1985},{"personId":"77588","playerName":"Larry Micheaux","building":"The Omni","slug":"the-omni","city":"Atlanta","city_slug":"atlanta","buildingType":"home","gameType":"Regular Season","games":2,"wins":1,"losses":1,"win_pct":0.5,"total_points":16,"ppg":8.0,"career_high":16,"first_season":1985,"last_season":1985},{"personId":"77588","playerName":"Larry Micheaux","building":"The Spectrum","slug":"the-spectrum","city":"Philadelphia","city_slug":"philadelphia","buildingType":"home","gameType":"Regular Season","games":3,"wins":0,"losses":3,"win_pct":0.0,"total_points":4,"ppg":1.3,"career_high":2,"first_season":1984,"last_season":1985},{"personId":"77588","playerName":"Larry Micheaux","building":"The Summit","slug":"the-summit","city":"Houston","city_slug":"houston","buildingType":"home","gameType":"Playoffs","games":3,"wins":1,"losses":2,"win_pct":0.333,"total_points":16,"ppg":5.3,"career_high":9,"first_season":1985,"last_season":1985},{"personId":"77588","playerName":"Larry Micheaux","building":"The Summit","slug":"the-summit","city":"Houston","city_slug":"houston","buildingType":"home","gameType":"Regular Season","games":22,"wins":16,"losses":6,"win_pct":0.727,"total_points":104,"ppg":4.7,"career_high":14,"first_season":1984,"last_season":1985}],"records_by_season":[{"building":"Arizona Veterans Memorial Coliseum","slug":"arizona-veterans-memorial-coliseum","city":"Phoenix","city_slug":"phoenix","buildingType":"home","gameType":"Regular Season","season":1984,"games":2,"wins":0,"losses":2,"win_pct":0.0,"total_points":2,"ppg":1.0,"career_high":2},{"building":"Arizona Veterans Memorial Coliseum","slug":"arizona-veterans-memorial-coliseum","city":"Phoenix","city_slug":"phoenix","buildingType":"home","gameType":"Regular Season","season":1985,"games":2,"wins":1,"losses":1,"win_pct":0.5,"total_points":13,"ppg":6.5,"career_high":7},{"building":"Boston Garden","slug":"boston-garden","city":"Boston","city_slug":"boston","buildingType":"home","gameType":"Regular Season","season":1985,"games":1,"wins":0,"losses":1,"win_pct":0.0,"total_points":7,"ppg":7.0,"career_high":7},{"building":"Capital Centre","slug":"capital-centre","city":"Landover","city_slug":"landover","buildingType":"home","gameType":"Regular Season","season":1985,"games":2,"wins":0,"losses":2,"win_pct":0.0,"total_points":0,"ppg":0.0,"career_high":0},{"building":"Chicago Stadium","slug":"chicago-stadium","city":"Chicago","city_slug":"chicago","buildingType":"home","gameType":"Regular Season","season":1985,"games":1,"wins":0,"losses":1,"win_pct":0.0,"total_points":0,"ppg":0.0,"career_high":0},{"building":"HemisFair Arena","slug":"hemisfair-arena","city":"San Antonio","city_slug":"san-antonio","buildingType":"home","gameType":"Regular Season","season":1984,"games":2,"wins":1,"losses":1,"win_pct":0.5,"total_points":2,"ppg":1.0,"career_high":2},{"building":"HemisFair Arena","slug":"hemisfair-arena","city":"San Antonio","city_slug":"san-antonio","buildingType":"home","gameType":"Regular Season","season":1985,"games":2,"wins":1,"losses":1,"win_pct":0.5,"total_points":5,"ppg":2.5,"career_high":5},{"building":"Kemper Arena","slug":"kemper-arena","city":"Kansas City","city_slug":"kansas-city","buildingType":"home","gameType":"Playoffs","season":1984,"games":1,"wins":0,"losses":1,"win_pct":0.0,"total_points":16,"ppg":16.0,"career_high":16},{"building":"Kemper Arena","slug":"kemper-arena","city":"Kansas City","city_slug":"kansas-city","buildingType":"home","gameType":"Regular Season","season":1984,"games":16,"wins":13,"losses":3,"win_pct":0.812,"total_points":56,"ppg":3.5,"career_high":15},{"building":"Kemper Arena","slug":"kemper-arena","city":"Kansas City","city_slug":"kansas-city","buildingType":"home","gameType":"Regular Season","season":1985,"games":1,"wins":1,"losses":0,"win_pct":1.0,"total_points":7,"ppg":7.0,"career_high":7},{"building":"Kingdome","slug":"kingdome","city":"Seattle","city_slug":"seattle","buildingType":"home","gameType":"Regular Season","season":1984,"games":1,"wins":0,"losses":1,"win_pct":0.0,"total_points":0,"ppg":0.0,"career_high":0},{"building":"Kingdome","slug":"kingdome","city":"Seattle","city_slug":"seattle","buildingType":"home","gameType":"Regular Season","season":1985,"games":1,"wins":1,"losses":0,"win_pct":1.0,"total_points":12,"ppg":12.0,"career_high":12},{"building":"MECCA Arena","slug":"mecca-arena","city":"Milwaukee","city_slug":"milwaukee","buildingType":"home","gameType":"Regular Season","season":1985,"games":8,"wins":8,"losses":0,"win_pct":1.0,"total_points":15,"ppg":1.9,"career_high":7},{"building":"Market Square Arena","slug":"market-square-arena","city":"Indianapolis","city_slug":"indianapolis","buildingType":"home","gameType":"Regular Season","season":1985,"games":1,"wins":0,"losses":1,"win_pct":0.0,"total_points":0,"ppg":0.0,"career_high":0},{"building":"McNichols Sports Arena","slug":"mcnichols-sports-arena","city":"Denver","city_slug":"denver","buildingType":"home","gameType":"Regular Season","season":1984,"games":1,"wins":0,"losses":1,"win_pct":0.0,"total_points":6,"ppg":6.0,"career_high":6},{"building":"McNichols Sports Arena","slug":"mcnichols-sports-arena","city":"Denver","city_slug":"denver","buildingType":"home","gameType":"Regular Season","season":1985,"games":1,"wins":0,"losses":1,"win_pct":0.0,"total_points":3,"ppg":3.0,"career_high":3},{"building":"Memorial Coliseum","slug":"memorial-coliseum","city":"Portland","city_slug":"portland","buildingType":"home","gameType":"Regular Season","season":1984,"games":2,"wins":0,"losses":2,"win_pct":0.0,"total_points":8,"ppg":4.0,"career_high":5},{"building":"Memorial Coliseum","slug":"memorial-coliseum","city":"Portland","city_slug":"portland","buildingType":"home","gameType":"Regular Season","season":1985,"games":2,"wins":0,"losses":2,"win_pct":0.0,"total_points":4,"ppg":2.0,"career_high":4},{"building":"Oracle Arena","slug":"oracle-arena","city":"Oakland","city_slug":"oakland","buildingType":"home","gameType":"Regular Season","season":1984,"games":2,"wins":0,"losses":2,"win_pct":0.0,"total_points":2,"ppg":1.0,"career_high":2},{"building":"Oracle Arena","slug":"oracle-arena","city":"Oakland","city_slug":"oakland","buildingType":"home","gameType":"Regular Season","season":1985,"games":2,"wins":1,"losses":1,"win_pct":0.5,"total_points":0,"ppg":0.0,"career_high":0},{"building":"Pontiac Silverdome","slug":"pontiac-silverdome","city":"Pontiac","city_slug":"pontiac","buildingType":"home","gameType":"Regular Season","season":1984,"games":1,"wins":0,"losses":1,"win_pct":0.0,"total_points":7,"ppg":7.0,"career_high":7},{"building":"Pontiac Silverdome","slug":"pontiac-silverdome","city":"Pontiac","city_slug":"pontiac","buildingType":"home","gameType":"Regular Season","season":1985,"games":2,"wins":0,"losses":2,"win_pct":0.0,"total_points":6,"ppg":3.0,"career_high":4},{"building":"Reunion Arena","slug":"reunion-arena","city":"Dallas","city_slug":"dallas","buildingType":"home","gameType":"Regular Season","season":1984,"games":3,"wins":0,"losses":3,"win_pct":0.0,"total_points":4,"ppg":1.3,"career_high":2},{"building":"Reunion Arena","slug":"reunion-arena","city":"Dallas","city_slug":"dallas","buildingType":"home","gameType":"Regular Season","season":1985,"games":2,"wins":1,"losses":1,"win_pct":0.5,"total_points":15,"ppg":7.5,"career_high":12},{"building":"Richfield Coliseum","slug":"richfield-coliseum","city":"Richfield","city_slug":"richfield","buildingType":"home","gameType":"Regular Season","season":1984,"games":1,"wins":1,"losses":0,"win_pct":1.0,"total_points":0,"ppg":0.0,"career_high":0},{"building":"Richfield Coliseum","slug":"richfield-coliseum","city":"Richfield","city_slug":"richfield","buildingType":"home","gameType":"Regular Season","season":1985,"games":1,"wins":1,"losses":0,"win_pct":1.0,"total_points":2,"ppg":2.0,"career_high":2},{"building":"Salt Palace","slug":"salt-palace","city":"Salt Lake City","city_slug":"salt-lake-city","buildingType":"home","gameType":"Playoffs","season":1985,"games":2,"wins":1,"losses":1,"win_pct":0.5,"total_points":0,"ppg":0.0,"career_high":0},{"building":"Salt Palace","slug":"salt-palace","city":"Salt Lake City","city_slug":"salt-lake-city","buildingType":"home","gameType":"Regular Season","season":1984,"games":2,"wins":0,"losses":2,"win_pct":0.0,"total_points":6,"ppg":3.0,"career_high":4},{"building":"Salt Palace","slug":"salt-palace","city":"Salt Lake City","city_slug":"salt-lake-city","buildingType":"home","gameType":"Regular Season","season":1985,"games":2,"wins":1,"losses":1,"win_pct":0.5,"total_points":2,"ppg":1.0,"career_high":2},{"building":"San Diego Sports Arena","slug":"san-diego-sports-arena","city":"San Diego","city_slug":"san-diego","buildingType":"home","gameType":"Regular Season","season":1984,"games":2,"wins":1,"losses":1,"win_pct":0.5,"total_points":10,"ppg":5.0,"career_high":10},{"building":"The Forum","slug":"the-forum","city":"Inglewood","city_slug":"inglewood","buildingType":"home","gameType":"Playoffs","season":1984,"games":2,"wins":0,"losses":2,"win_pct":0.0,"total_points":14,"ppg":7.0,"career_high":8},{"building":"The Forum","slug":"the-forum","city":"Inglewood","city_slug":"inglewood","buildingType":"home","gameType":"Regular Season","season":1984,"games":2,"wins":0,"losses":2,"win_pct":0.0,"total_points":12,"ppg":6.0,"career_high":6},{"building":"The Forum","slug":"the-forum","city":"Inglewood","city_slug":"inglewood","buildingType":"home","gameType":"Regular Season","season":1985,"games":1,"wins":1,"losses":0,"win_pct":1.0,"total_points":0,"ppg":0.0,"career_high":0},{"building":"The Omni","slug":"the-omni","city":"Atlanta","city_slug":"atlanta","buildingType":"home","gameType":"Regular Season","season":1985,"games":2,"wins":1,"losses":1,"win_pct":0.5,"total_points":16,"ppg":8.0,"career_high":16},{"building":"The Spectrum","slug":"the-spectrum","city":"Philadelphia","city_slug":"philadelphia","buildingType":"home","gameType":"Regular Season","season":1984,"games":1,"wins":0,"losses":1,"win_pct":0.0,"total_points":2,"ppg":2.0,"career_high":2},{"building":"The Spectrum","slug":"the-spectrum","city":"Philadelphia","city_slug":"philadelphia","buildingType":"home","gameType":"Regular Season","season":1985,"games":2,"wins":0,"losses":2,"win_pct":0.0,"total_points":2,"ppg":1.0,"career_high":2},{"building":"The Summit","slug":"the-summit","city":"Houston","city_slug":"houston","buildingType":"home","gameType":"Playoffs","season":1985,"games":3,"wins":1,"losses":2,"win_pct":0.333,"total_points":16,"ppg":5.3,"career_high":9},{"building":"The Summit","slug":"the-summit","city":"Houston","city_slug":"houston","buildingType":"home","gameType":"Regular Season","season":1984,"games":1,"wins":1,"losses":0,"win_pct":1.0,"total_points":2,"ppg":2.0,"career_high":2},{"building":"The Summit","slug":"the-summit","city":"Houston","city_slug":"houston","buildingType":"home","gameType":"Regular Season","season":1985,"games":21,"wins":15,"losses":6,"win_pct":0.714,"total_points":102,"ppg":4.9,"career_high":14}],"arena_draw":[],"draw_label":"1983-84 – 1984-85","arena_draw_by_season":{"1984":[{"arena":"Arizona Veterans Memorial Coliseum","slug":"arizona-veterans-memorial-coliseum","city":"Phoenix","city_slug":"phoenix","games":1,"mean_delta":2884.0},{"arena":"The Spectrum","slug":"the-spectrum","city":"Philadelphia","city_slug":"philadelphia","games":1,"mean_delta":1555.6},{"arena":"McNichols Sports Arena","slug":"mcnichols-sports-arena","city":"Denver","city_slug":"denver","games":1,"mean_delta":791.6},{"arena":"Salt Palace","slug":"salt-palace","city":"Salt Lake City","city_slug":"salt-lake-city","games":1,"mean_delta":-530.8},{"arena":"Reunion Arena","slug":"reunion-arena","city":"Dallas","city_slug":"dallas","games":3,"mean_delta":-602.6},{"arena":"HemisFair Arena","slug":"hemisfair-arena","city":"San Antonio","city_slug":"san-antonio","games":1,"mean_delta":-695.3},{"arena":"The Forum","slug":"the-forum","city":"Inglewood","city_slug":"inglewood","games":3,"mean_delta":-881.7},{"arena":"Oracle Arena","slug":"oracle-arena","city":"Oakland","city_slug":"oakland","games":2,"mean_delta":-1053.5},{"arena":"Kingdome","slug":"kingdome","city":"Seattle","city_slug":"seattle","games":1,"mean_delta":-1622.1},{"arena":"Richfield Coliseum","slug":"richfield-coliseum","city":"Richfield","city_slug":"richfield","games":1,"mean_delta":-2465.2},{"arena":"Pontiac Silverdome","slug":"pontiac-silverdome","city":"Pontiac","city_slug":"pontiac","games":1,"mean_delta":-5795.0}],"1985":[{"arena":"Oracle Arena","slug":"oracle-arena","city":"Oakland","city_slug":"oakland","games":1,"mean_delta":6076.2},{"arena":"Pontiac Silverdome","slug":"pontiac-silverdome","city":"Pontiac","city_slug":"pontiac","games":1,"mean_delta":5508.8},{"arena":"HemisFair Arena","slug":"hemisfair-arena","city":"San Antonio","city_slug":"san-antonio","games":2,"mean_delta":3197.5},{"arena":"The Forum","slug":"the-forum","city":"Inglewood","city_slug":"inglewood","games":1,"mean_delta":2682.9},{"arena":"Salt Palace","slug":"salt-palace","city":"Salt Lake City","city_slug":"salt-lake-city","games":2,"mean_delta":1890.0},{"arena":"Kemper Arena","slug":"kemper-arena","city":"Kansas City","city_slug":"kansas-city","games":1,"mean_delta":1258.4},{"arena":"Arizona Veterans Memorial Coliseum","slug":"arizona-veterans-memorial-coliseum","city":"Phoenix","city_slug":"phoenix","games":1,"mean_delta":1064.7},{"arena":"Reunion Arena","slug":"reunion-arena","city":"Dallas","city_slug":"dallas","games":2,"mean_delta":89.0},{"arena":"Memorial Coliseum","slug":"memorial-coliseum","city":"Portland","city_slug":"portland","games":2,"mean_delta":-0.2},{"arena":"The Spectrum","slug":"the-spectrum","city":"Philadelphia","city_slug":"philadelphia","games":2,"mean_delta":-282.3},{"arena":"Kingdome","slug":"kingdome","city":"Seattle","city_slug":"seattle","games":1,"mean_delta":-876.2},{"arena":"Capital Centre","slug":"capital-centre","city":"Landover","city_slug":"landover","games":1,"mean_delta":-1666.9},{"arena":"Chicago Stadium","slug":"chicago-stadium","city":"Chicago","city_slug":"chicago","games":1,"mean_delta":-2446.8},{"arena":"Market Square Arena","slug":"market-square-arena","city":"Indianapolis","city_slug":"indianapolis","games":1,"mean_delta":-3208.6},{"arena":"The Omni","slug":"the-omni","city":"Atlanta","city_slug":"atlanta","games":2,"mean_delta":-3633.8},{"arena":"Richfield Coliseum","slug":"richfield-coliseum","city":"Richfield","city_slug":"richfield","games":1,"mean_delta":-4586.1}],"all":[{"arena":"Arizona Veterans Memorial Coliseum","slug":"arizona-veterans-memorial-coliseum","city":"Phoenix","city_slug":"phoenix","games":2,"mean_delta":1974.3},{"arena":"HemisFair Arena","slug":"hemisfair-arena","city":"San Antonio","city_slug":"san-antonio","games":3,"mean_delta":1899.9},{"arena":"Oracle Arena","slug":"oracle-arena","city":"Oakland","city_slug":"oakland","games":3,"mean_delta":1323.1},{"arena":"Kemper Arena","slug":"kemper-arena","city":"Kansas City","city_slug":"kansas-city","games":1,"mean_delta":1258.4},{"arena":"Salt Palace","slug":"salt-palace","city":"Salt Lake City","city_slug":"salt-lake-city","games":3,"mean_delta":1083.1},{"arena":"McNichols Sports Arena","slug":"mcnichols-sports-arena","city":"Denver","city_slug":"denver","games":1,"mean_delta":791.6},{"arena":"The Spectrum","slug":"the-spectrum","city":"Philadelphia","city_slug":"philadelphia","games":3,"mean_delta":330.3},{"arena":"The Forum","slug":"the-forum","city":"Inglewood","city_slug":"inglewood","games":4,"mean_delta":9.4},{"arena":"Memorial Coliseum","slug":"memorial-coliseum","city":"Portland","city_slug":"portland","games":2,"mean_delta":-0.2},{"arena":"Pontiac Silverdome","slug":"pontiac-silverdome","city":"Pontiac","city_slug":"pontiac","games":2,"mean_delta":-143.1},{"arena":"Reunion Arena","slug":"reunion-arena","city":"Dallas","city_slug":"dallas","games":5,"mean_delta":-326.0},{"arena":"Kingdome","slug":"kingdome","city":"Seattle","city_slug":"seattle","games":2,"mean_delta":-1249.2},{"arena":"Capital Centre","slug":"capital-centre","city":"Landover","city_slug":"landover","games":1,"mean_delta":-1666.9},{"arena":"Chicago Stadium","slug":"chicago-stadium","city":"Chicago","city_slug":"chicago","games":1,"mean_delta":-2446.8},{"arena":"Market Square Arena","slug":"market-square-arena","city":"Indianapolis","city_slug":"indianapolis","games":1,"mean_delta":-3208.6},{"arena":"Richfield Coliseum","slug":"richfield-coliseum","city":"Richfield","city_slug":"richfield","games":2,"mean_delta":-3525.7},{"arena":"The Omni","slug":"the-omni","city":"Atlanta","city_slug":"atlanta","games":2,"mean_delta":-3633.8}]},"draw_seasons":[1984,1985]}